{
	"configurations" : 
	[
		{
			"directories" : 
			[
				{
					"build" : ".",
					"jsonFile" : "directory-.-Debug-f5ebdc15457944623624.json",
					"minimumCMakeVersion" : 
					{
						"string" : "3.1"
					},
					"projectIndex" : 0,
					"source" : ".",
					"targetIndexes" : 
					[
						0,
						1,
						2
					]
				}
			],
			"name" : "Debug",
			"projects" : 
			[
				{
					"directoryIndexes" : 
					[
						0
					],
					"name" : "wgraph",
					"targetIndexes" : 
					[
						0,
						1,
						2
					]
				}
			],
			"targets" : 
			[
				{
					"directoryIndex" : 0,
					"id" : "test_create_graph::@6890427a1f51a3e7e1df",
					"jsonFile" : "target-test_create_graph-Debug-2241839f16fda9f4bb57.json",
					"name" : "test_create_graph",
					"projectIndex" : 0
				},
				{
					"directoryIndex" : 0,
					"id" : "test_wgraph::@6890427a1f51a3e7e1df",
					"jsonFile" : "target-test_wgraph-Debug-344201524af0d5b72354.json",
					"name" : "test_wgraph",
					"projectIndex" : 0
				},
				{
					"directoryIndex" : 0,
					"id" : "wgraph::@6890427a1f51a3e7e1df",
					"jsonFile" : "target-wgraph-Debug-a8a5bd4632f82ea19e13.json",
					"name" : "wgraph",
					"projectIndex" : 0
				}
			]
		}
	],
	"kind" : "codemodel",
	"paths" : 
	{
		"build" : "/home/mayumar/Escritorio/practicased/wgraph_paths/build-wgraph-Desktop-Debug",
		"source" : "/home/mayumar/Escritorio/practicased/wgraph_paths/wgraph"
	},
	"version" : 
	{
		"major" : 2,
		"minor" : 4
	}
}
